impulsePy/__init__.py
impulsePy-3.0.0.dist-info/LICENSE
impulsePy-3.0.0.dist-info/METADATA
impulsePy-3.0.0.dist-info/WHEEL
impulsePy-3.0.0.dist-info/top_level.txt
impulsePy-3.0.0.dist-info/RECORD
