Metadata-Version: 2.1
Name: impulsePy
Version: 3.0.0
Summary: Library for controlling Impulse
Home-page: 
Author: DENSsolutions
Author-email: merijn.pen@DENSsolutions.com
Classifier: Programming Language :: Python :: 3
Classifier: License :: OSI Approved :: MIT License
Classifier: Operating System :: OS Independent
Requires-Python: >=3.6
License-File: LICENSE
Requires-Dist: zmq
Requires-Dist: pandas
Requires-Dist: numpy
